imfeatures/__init__.py
imfeatures/features.py
imfeatures-0.0.2.dist-info/LICENSE.md
imfeatures-0.0.2.dist-info/METADATA
imfeatures-0.0.2.dist-info/WHEEL
imfeatures-0.0.2.dist-info/top_level.txt
imfeatures-0.0.2.dist-info/RECORD
