Metadata-Version: 2.1
Name: imfeatures
Version: 0.0.2
Summary: Python package to extract deep learning features 
Home-page: https://github.com/resbyte/imfeatures
Author: Abhinav Dadhich
Author-email: abhinavvicku@gmail.com
License: BSD
Download-URL: https://github.com/resbyte/imfeatures/tarball/0.0.2
Platform: UNKNOWN
Classifier: Development Status :: 3 - Alpha
Classifier: Intended Audience :: Developers
Classifier: Programming Language :: Python :: 3
Requires-Dist: sphinx
Requires-Dist: sphinx-rtd-theme
Requires-Dist: nose
Requires-Dist: coverage
Requires-Dist: pypi-publisher
Requires-Dist: torch
Requires-Dist: torchvision
